{"h":{"1232268959970103337":{"_record":{"data":{"h":{}}},"name":"test","threadid":"1232268959970103337","count":5,"id":1},"1202383067373637642":{"_record":{"data":{"h":{"id":2,"name":"fnf","threadid":"1202383067373637642","count":332009}}},"name":"fnf","threadid":"1202383067373637642","count":332010,"id":2},"956928971927339018":{"_record":{"data":{"h":{}}},"name":"linux nerds - 3 days since stefan last changed his distro","threadid":"956928971927339018","count":46601,"id":3},"1234939525931728906":{"_record":{"data":{"h":{}}},"name":"💀 cortex","threadid":"1234939525931728906","count":14108,"id":4},"1256674797195104336":{"_record":{"data":{"h":{}}},"name":"hanako","threadid":"1256674797195104336","count":60,"id":5},"1253824066695987311":{"_record":{"data":{"h":{}}},"name":"auto-rpg","threadid":"1253824066695987311","count":62,"id":8},"1259843001727844392":{"_record":{"data":{"h":{}}},"name":"i've learned haxeflixel for like 3 / 4","threadid":"1259843001727844392","count":31,"id":10},"1190890266450743297":{"_record":{"data":{"h":{}}},"name":"undertale purple","threadid":"1190890266450743297","count":1438,"id":11},"1255964895489560759":{"_record":{"data":{"h":{}}},"name":"one must imagine sisyphus happy","threadid":"1255964895489560759","count":1,"id":13},"1024001628560429128":{"_record":{"data":{"h":{}}},"name":"renaine stuff","threadid":"1024001628560429128","count":151,"id":14},"1057306134534443048":{"_record":{"data":{"h":{}}},"name":"core haxe","threadid":"1057306134534443048","count":5481,"id":16},"1261057062390075503":{"_record":{"data":{"h":{}}},"name":"it does seem to be a linking order issue","threadid":"1261057062390075503","count":4,"id":18},"1261127692099780709":{"_record":{"data":{"h":{}}},"name":"eggu's silly jumping game (weewahooyeah)","threadid":"1261127692099780709","count":1,"id":20},"1261403996728328263":{"_record":{"data":{"h":{}}},"name":"rap-it-up / indev","threadid":"1261403996728328263","count":100,"id":21},"1234218972896039002":{"_record":{"data":{"h":{}}},"name":"lemons","threadid":"1234218972896039002","count":522,"id":23},"1261441082491670579":{"_record":{"data":{"h":{}}},"name":"the jumping game i made in less than 3 hours - update 1","threadid":"1261441082491670579","count":5,"id":24},"928268555160526898":{"_record":{"data":{"h":{}}},"name":"aidanecs","threadid":"928268555160526898","count":17,"id":26},"1262894332210577549":{"_record":{"data":{"h":{}}},"name":"show the code that doesnt do anything","threadid":"1262894332210577549","count":2,"id":28},"1020047935234387979":{"_record":{"data":{"h":{}}},"name":"haxebot","threadid":"1020047935234387979","count":808,"id":30},"1263261784043814933":{"_record":{"data":{"h":{}}},"name":"i think you should change that to array<string>'s","threadid":"1263261784043814933","count":5,"id":31},"1129740232502292490":{"_record":{"data":{"h":{}}},"name":"evil haxe","threadid":"1129740232502292490","count":20,"id":34},"1264651178126475487":{"_record":{"data":{"h":{}}},"name":"tony jumpman","threadid":"1264651178126475487","count":6,"id":36},"1211352204628328578":{"_record":{"data":{"h":{}}},"name":"hololive card adventure - wip","threadid":"1211352204628328578","count":60,"id":37},"1264549533589966960":{"_record":{"data":{"h":{}}},"name":"tagg - textures and graffiti generator","threadid":"1264549533589966960","count":31,"id":39},"1266366717307650101":{"_record":{"data":{"h":{}}},"name":"tilbuci","threadid":"1266366717307650101","count":42,"id":40},"1172565073655496754":{"_record":{"data":{"h":{}}},"name":"fnaf series recreation","threadid":"1172565073655496754","count":24,"id":41},"1096816414880440560":{"_record":{"data":{"h":{}}},"name":"intellij haxe plugin","threadid":"1096816414880440560","count":786,"id":43},"1019946163417399327":{"_record":{"data":{"h":{}}},"name":"haxeui updates","threadid":"1019946163417399327","count":6,"id":46},"1268345356769427457":{"_record":{"data":{"h":{}}},"name":"rock paper scissors in flowscript which","threadid":"1268345356769427457","count":6,"id":47},"1140615400770519122":{"_record":{"data":{"h":{}}},"name":"power line rider","threadid":"1140615400770519122","count":190,"id":49},"1268509269104525352":{"_record":{"data":{"h":{}}},"name":"genkit: create dangerously efficient bindings","threadid":"1268509269104525352","count":540,"id":51},"1270523924697972837":{"_record":{"data":{"h":{}}},"name":"chill room","threadid":"1270523924697972837","count":62,"id":52},"1268580889734942882":{"_record":{"data":{"h":{}}},"name":"flowscript","threadid":"1268580889734942882","count":41,"id":54},"1233774792872693783":{"_record":{"data":{"h":{}}},"name":"flappy bird level editor","threadid":"1233774792872693783","count":1,"id":55},"1273631446862401596":{"_record":{"data":{"h":{}}},"name":"real-time peer mesh protocol (rtpmp)","threadid":"1273631446862401596","count":36,"id":56},"1239467248263892993":{"_record":{"data":{"h":{}}},"name":"trading journal/home base app","threadid":"1239467248263892993","count":1860,"id":57},"1274829188888657920":{"_record":{"data":{"h":{}}},"name":"do you know if there's any guide on","threadid":"1274829188888657920","count":1,"id":59},"1021250535405404170":{"_record":{"data":{"h":{}}},"name":"wild west roguelike","threadid":"1021250535405404170","count":4,"id":60},"1273459126260859011":{"_record":{"data":{"h":{}}},"name":"like lists hold extra references while","threadid":"1273459126260859011","count":9,"id":62},"1276629573773033494":{"_record":{"data":{"h":{}}},"name":"genesis","threadid":"1276629573773033494","count":7,"id":64},"1232805485196087456":{"_record":{"data":{"h":{}}},"name":"flxsvg - svg render for haxeflixel","threadid":"1232805485196087456","count":50,"id":67},"1278899928680108032":{"_record":{"data":{"h":{}}},"name":"tsa fighter - a dev log","threadid":"1278899928680108032","count":15,"id":68},"1277966616222629971":{"_record":{"data":{"h":{}}},"name":"> for developers and distributors of","threadid":"1277966616222629971","count":15,"id":69},"1279882430060171274":{"_record":{"data":{"h":{}}},"name":"wuddy game","threadid":"1279882430060171274","count":1,"id":70},"1280490008456855582":{"_record":{"data":{"h":{}}},"name":"enums for json - work fine or not?","threadid":"1280490008456855582","count":2,"id":72},"1240255391493783552":{"_record":{"data":{"h":{}}},"name":"hxvlc","threadid":"1240255391493783552","count":658,"id":74},"1276627002022953000":{"_record":{"data":{"h":{}}},"name":"genesis: a haxe rendering library","threadid":"1276627002022953000","count":1244,"id":75},"1281944449362165811":{"_record":{"data":{"h":{}}},"name":"haxebuild","threadid":"1281944449362165811","count":68,"id":76},"1278702233445466184":{"_record":{"data":{"h":{}}},"name":"tony's crazy adventures!","threadid":"1278702233445466184","count":10,"id":78},"1036324542064373760":{"_record":{"data":{"h":{}}},"name":"a very limited 3d renderer with flixel","threadid":"1036324542064373760","count":4,"id":80},"1281990870156968047":{"_record":{"data":{"h":{}}},"name":"flxos (w.i.p)","threadid":"1281990870156968047","count":131,"id":83},"1202862068961910794":{"_record":{"data":{"h":{}}},"name":"modifaxe","threadid":"1202862068961910794","count":7,"id":85},"1287128521851797635":{"_record":{"data":{"h":{}}},"name":"isometric voxel engine","threadid":"1287128521851797635","count":11,"id":86},"1287443283911381094":{"_record":{"data":{"h":{}}},"name":"ceramic memes","threadid":"1287443283911381094","count":30,"id":88},"1288493533384151044":{"_record":{"data":{"h":{}}},"name":"thor, an alternative to hide for heaps/hashlink","threadid":"1288493533384151044","count":47,"id":90},"1218777660134527068":{"_record":{"data":{"h":{}}},"name":"multithreading","threadid":"1218777660134527068","count":16,"id":92},"1291000458978005103":{"_record":{"data":{"h":{}}},"name":"hlfmod","threadid":"1291000458978005103","count":1,"id":94},"1293002539012198472":{"_record":{"data":{"h":{}}},"name":"triflings","threadid":"1293002539012198472","count":1,"id":96},"1293336503107321936":{"_record":{"data":{"h":{}}},"name":"interstellar cargo maidens","threadid":"1293336503107321936","count":6,"id":97},"1294013232779886592":{"_record":{"data":{"h":{}}},"name":"i feel like mutex is too much for a","threadid":"1294013232779886592","count":25,"id":100},"1244844583838421112":{"_record":{"data":{"h":{}}},"name":"teetoe game","threadid":"1244844583838421112","count":183,"id":101},"1020028722042118214":{"_record":{"data":{"h":{}}},"name":"vision - cv & im library","threadid":"1020028722042118214","count":21,"id":102},"1213817424680456222":{"_record":{"data":{"h":{}}},"name":"windows 95 heaps edition","threadid":"1213817424680456222","count":10,"id":104},"1296199679763284038":{"_record":{"data":{"h":{}}},"name":"flx-rpg","threadid":"1296199679763284038","count":55,"id":105},"1297857642307256320":{"_record":{"data":{"h":{}}},"name":"documentation","threadid":"1297857642307256320","count":38,"id":108},"1047091991852367892":{"_record":{"data":{"h":{}}},"name":"flxanimate","threadid":"1047091991852367892","count":58,"id":109},"1133094294144684163":{"_record":{"data":{"h":{}}},"name":"haxeal soft - native c++ bindings for openal soft 1.23.1","threadid":"1133094294144684163","count":434,"id":110},"1216534573689868428":{"_record":{"data":{"h":{}}},"name":"hxbun - experimental haxe externs for bun","threadid":"1216534573689868428","count":1,"id":111},"1299769628880539742":{"_record":{"data":{"h":{}}},"name":"acrylic shader","threadid":"1299769628880539742","count":1,"id":113},"1297978372529586207":{"_record":{"data":{"h":{}}},"name":"wisdom, loreline (jeremy stuff in haxe)","threadid":"1297978372529586207","count":13128,"id":114},"1302027506853085346":{"_record":{"data":{"h":{}}},"name":"flixel raylib","threadid":"1302027506853085346","count":189,"id":115},"1301887721043787827":{"_record":{"data":{"h":{}}},"name":"hldiscord_rpc","threadid":"1301887721043787827","count":48,"id":116},"1298393984908922942":{"_record":{"data":{"h":{}}},"name":"hxbun - experimental haxe externs for bun, a fast javascript runtime","threadid":"1298393984908922942","count":10,"id":117},"1304469145529745429":{"_record":{"data":{"h":{}}},"name":"interesting, tbf, the way i'm going","threadid":"1304469145529745429","count":6,"id":118},"1299578584930844784":{"_record":{"data":{"h":{}}},"name":"hxcord - discord api/bot library","threadid":"1299578584930844784","count":161,"id":119},"1304533048532013167":{"_record":{"data":{"h":{}}},"name":"cheese rat - ritz inspired platformer","threadid":"1304533048532013167","count":18,"id":120},"1300887584180011151":{"_record":{"data":{"h":{}}},"name":"ponto final","threadid":"1300887584180011151","count":10,"id":122},"1307323307389095956":{"_record":{"data":{"h":{}}},"name":"berothe","threadid":"1307323307389095956","count":60,"id":123},"1306016575530467358":{"_record":{"data":{"h":{}}},"name":"beginnings of \"dashboard editor\" for a","threadid":"1306016575530467358","count":4,"id":124},"1307692113634398309":{"_record":{"data":{"h":{}}},"name":"how would  i be able to like uhh switch","threadid":"1307692113634398309","count":12,"id":126},"1304876682863317033":{"_record":{"data":{"h":{}}},"name":"ui layout:","threadid":"1304876682863317033","count":2,"id":128},"1309155337235992607":{"_record":{"data":{"h":{}}},"name":"moonshine.dev: a new tool for streamlined ui design in haxe with feathers ui","threadid":"1309155337235992607","count":12,"id":129},"1307366386762518619":{"_record":{"data":{"h":{}}},"name":"platformer (nameless)","threadid":"1307366386762518619","count":2,"id":130},"1309811859213254686":{"_record":{"data":{"h":{}}},"name":"ssl cert verification error on windows","threadid":"1309811859213254686","count":68,"id":131},"1310349422311505981":{"_record":{"data":{"h":{}}},"name":"haxe http server base","threadid":"1310349422311505981","count":1,"id":133},"1312162719993958481":{"_record":{"data":{"h":{"id":134,"name":"rulescript & ruleparsers","threadid":"1312162719993958481","count":16088}}},"name":"rulescript & ruleparsers","threadid":"1312162719993958481","count":16088,"id":134},"1311408659036766238":{"_record":{"data":{"h":{}}},"name":"pixel art editor","threadid":"1311408659036766238","count":6,"id":135},"1309156074447962186":{"_record":{"data":{"h":{}}},"name":"introducing moonshine.dev: a new tool fo...","threadid":"1309156074447962186","count":31,"id":137},"1311129828069740604":{"_record":{"data":{"h":{}}},"name":"funkin' view by :;d26","threadid":"1311129828069740604","count":4618,"id":138},"1313163849402421351":{"_record":{"data":{"h":{}}},"name":"note","threadid":"1313163849402421351","count":2,"id":139},"1313443875829973064":{"_record":{"data":{"h":{}}},"name":"haxe dependencies viewer","threadid":"1313443875829973064","count":716,"id":140},"1311529628736688178":{"_record":{"data":{"h":{}}},"name":"hashcord","threadid":"1311529628736688178","count":161,"id":141},"1313818103305601085":{"_record":{"data":{"h":{}}},"name":"i'm going to be late to starting, but i'","threadid":"1313818103305601085","count":3,"id":142},"1312171045737988096":{"_record":{"data":{"h":{}}},"name":"haxelib cleaner","threadid":"1312171045737988096","count":9,"id":143},"1314685227351932988":{"_record":{"data":{"h":{}}},"name":"haxeflixel android compilation error","threadid":"1314685227351932988","count":3,"id":144},"1313098658106966067":{"_record":{"data":{"h":{}}},"name":"hopefully it will work, i have complex","threadid":"1313098658106966067","count":88,"id":146},"1315301107467292742":{"_record":{"data":{"h":{}}},"name":"hexe - prefab editor and runtime library for the heaps game engine.","threadid":"1315301107467292742","count":163,"id":147},"1317651487572230154":{"_record":{"data":{"h":{}}},"name":"garbage day","threadid":"1317651487572230154","count":2,"id":148},"1313770898016178226":{"_record":{"data":{"h":{}}},"name":"hey rudy, what's going on here <https://","threadid":"1313770898016178226","count":80,"id":150},"1319372184686428282":{"_record":{"data":{"h":{}}},"name":"flixel vs ceramic (rap battle)","threadid":"1319372184686428282","count":7,"id":151},"1321479215027196014":{"_record":{"data":{"h":{}}},"name":"make has nothing to do with library","threadid":"1321479215027196014","count":2,"id":152},"1316048237626523740":{"_record":{"data":{"h":{}}},"name":"moonshine.dev - rapid app development & ...","threadid":"1316048237626523740","count":15,"id":154},"1322263529901789265":{"_record":{"data":{"h":{}}},"name":"ogmo layers problem","threadid":"1322263529901789265","count":36,"id":155},"1199745315243315332":{"_record":{"data":{"h":{}}},"name":"vortex game framework discussion","threadid":"1199745315243315332","count":1,"id":156},"1320091398149640222":{"_record":{"data":{"h":{}}},"name":"inner dimension reach b-sides","threadid":"1320091398149640222","count":37,"id":158},"1323573316711223378":{"_record":{"data":{"h":{}}},"name":"hello, i'm having trouble with my vscode","threadid":"1323573316711223378","count":1,"id":159},"1325553669957091379":{"_record":{"data":{"h":{}}},"name":"hey there! i posted this in #flixel","threadid":"1325553669957091379","count":72,"id":161},"1326867118687256576":{"_record":{"data":{"h":{}}},"name":"and then when a change is made deletes","threadid":"1326867118687256576","count":65,"id":162},"1322980856415129690":{"_record":{"data":{"h":{}}},"name":"nsance co.","threadid":"1322980856415129690","count":17,"id":164},"1327603348806832138":{"_record":{"data":{"h":{}}},"name":"thingmaker","threadid":"1327603348806832138","count":73,"id":165},"1180578838460235866":{"_record":{"data":{"h":{}}},"name":"preon demo, made with haxeflixel","threadid":"1180578838460235866","count":13,"id":166},"1328105531889422457":{"_record":{"data":{"h":{}}},"name":"flxcontrols - a simplified multi-device input manager tools for haxeflixel","threadid":"1328105531889422457","count":99,"id":167},"1326087366506708992":{"_record":{"data":{"h":{}}},"name":"i wonder, are vshaxe's `server.js`","threadid":"1326087366506708992","count":22,"id":169},"1328507225282576484":{"_record":{"data":{"h":{}}},"name":"logo's attempt at redesigning haxe.org's frontpage","threadid":"1328507225282576484","count":153,"id":170},"1327526684324270100":{"_record":{"data":{"h":{}}},"name":"sapphire engine","threadid":"1327526684324270100","count":17,"id":171},"924833220724416532":{"_record":{"data":{"h":{}}},"name":"aidans ecs","threadid":"924833220724416532","count":59,"id":173},"1327856212351520911":{"_record":{"data":{"h":{}}},"name":"help with some overlap logic","threadid":"1327856212351520911","count":26,"id":174},"1328514735196340224":{"_record":{"data":{"h":{}}},"name":"lunarps: the new flxemitter.","threadid":"1328514735196340224","count":70,"id":175},"1328514433529548922":{"_record":{"data":{"h":{}}},"name":"lunarlib: better general-framework features.","threadid":"1328514433529548922","count":4,"id":176},"1330621429267562646":{"_record":{"data":{"h":{}}},"name":"messing around with waveforms","threadid":"1330621429267562646","count":16,"id":177},"1253330375447547935":{"_record":{"data":{"h":{}}},"name":"how?","threadid":"1253330375447547935","count":122,"id":179},"1332951181114343434":{"_record":{"data":{"h":{}}},"name":"project dreamland","threadid":"1332951181114343434","count":12,"id":180},"1108515973012672583":{"_record":{"data":{"h":{}}},"name":"hxpy - haxe/hxcpp @:native bindings for python","threadid":"1108515973012672583","count":37,"id":181},"1333087787661922356":{"_record":{"data":{"h":{}}},"name":"hxopus","threadid":"1333087787661922356","count":24,"id":182},"1330198210391576658":{"_record":{"data":{"h":{}}},"name":"vastveil","threadid":"1330198210391576658","count":6,"id":184},"1335398066370515057":{"_record":{"data":{"h":{}}},"name":"hx_l2d","threadid":"1335398066370515057","count":12,"id":185},"1327217684848578613":{"_record":{"data":{"h":{}}},"name":"tested on one project:","threadid":"1327217684848578613","count":255,"id":186},"1336010142218715231":{"_record":{"data":{"h":{}}},"name":"king donkey","threadid":"1336010142218715231","count":6,"id":188},"1333162924377641063":{"_record":{"data":{"h":{}}},"name":"pac-man remake/clone in haxeflixel","threadid":"1333162924377641063","count":8,"id":189},"1337523422812700816":{"_record":{"data":{"h":{}}},"name":"haxe / #haxeui based \"glint analytics\"","threadid":"1337523422812700816","count":14,"id":190},"1340092502484586527":{"_record":{"data":{"h":{}}},"name":"there is a bug with a gc run trying to","threadid":"1340092502484586527","count":43,"id":191},"987488521021444106":{"_record":{"data":{"h":{}}},"name":"so maybe we open a thread logo0788","threadid":"987488521021444106","count":1,"id":192},"1341456099475193907":{"_record":{"data":{"h":{}}},"name":"renaine compile times thread","threadid":"1341456099475193907","count":61,"id":193},"1335418686659498044":{"_record":{"data":{"h":{}}},"name":"horse hole - finally, a horse based physics sandbox","threadid":"1335418686659498044","count":178,"id":194},"1335313106766925885":{"_record":{"data":{"h":{}}},"name":"teasting","threadid":"1335313106766925885","count":2,"id":195},"1342385771335647262":{"_record":{"data":{"h":{}}},"name":"petal - simple game/app framework","threadid":"1342385771335647262","count":20,"id":197},"1341823862396031136":{"_record":{"data":{"h":{}}},"name":"airpsx","threadid":"1341823862396031136","count":3,"id":198},"1344392407415914546":{"_record":{"data":{"h":{}}},"name":"anga dash reborn","threadid":"1344392407415914546","count":2,"id":200},"1343588927801393192":{"_record":{"data":{"h":{}}},"name":"# `lime test windows` fails with internal compiler error","threadid":"1343588927801393192","count":27,"id":203},"1256279332515741807":{"_record":{"data":{"h":{}}},"name":"kumoui: platform-agnostic immediate-mode gui","threadid":"1256279332515741807","count":758,"id":206},"1255067476534886521":{"_record":{"data":{"h":{}}},"name":"hxpkg","threadid":"1255067476534886521","count":89,"id":207},"1064446400231907348":{"_record":{"data":{"h":{}}},"name":"polymod","threadid":"1064446400231907348","count":688,"id":209},"1259888132002943069":{"_record":{"data":{"h":{}}},"name":"linetapper","threadid":"1259888132002943069","count":4295,"id":211},"1246845964690657452":{"_record":{"data":{"h":{}}},"name":"vortex - 2d game framework","threadid":"1246845964690657452","count":12,"id":220},"1260060068544647199":{"_record":{"data":{"h":{}}},"name":"haxenstein","threadid":"1260060068544647199","count":23,"id":223},"1261521114367131679":{"_record":{"data":{"h":{}}},"name":"as a large language model, i request","threadid":"1261521114367131679","count":7,"id":227},"1231408271139672127":{"_record":{"data":{"h":{}}},"name":"project: fts (foss fnaf fan game)","threadid":"1231408271139672127","count":5,"id":228},"1020312969361498112":{"_record":{"data":{"h":{}}},"name":"general","threadid":"1020312969361498112","count":129,"id":231},"1262767582671536138":{"_record":{"data":{"h":{}}},"name":"tyler's game","threadid":"1262767582671536138","count":11,"id":233},"1346125794136555543":{"_record":{"data":{"h":{}}},"name":"heykoffii,justtestingsomething,ignoreme","threadid":"1346125794136555543","count":3,"id":234},"1346226550315548742":{"_record":{"data":{"h":{}}},"name":"testing","threadid":"1346226550315548742","count":5,"id":235},"1346236801031082094":{"_record":{"data":{"h":{}}},"name":"new new thread","threadid":"1346236801031082094","count":12,"id":236},"1338080465642328134":{"_record":{"data":{"h":{}}},"name":"alcl","threadid":"1338080465642328134","count":244,"id":237},"1346835191699738766":{"_record":{"data":{"h":{}}},"name":"it looks like the code to detect cppia","threadid":"1346835191699738766","count":14,"id":238},"1345541217622163456":{"_record":{"data":{"h":{}}},"name":"hxcompileu: a way to create homebrew on the wii u, using haxe!","threadid":"1345541217622163456","count":102,"id":239},"1346849325984256112":{"_record":{"data":{"h":{}}},"name":"butte: a simplistic and opinionated framework/library to build web applications","threadid":"1346849325984256112","count":4,"id":240},"1340696952748376075":{"_record":{"data":{"h":{}}},"name":"flixel-waveform","threadid":"1340696952748376075","count":182,"id":241},"1307417138331648040":{"_record":{"data":{"h":{}}},"name":"bullet shine","threadid":"1307417138331648040","count":6,"id":242},"1209142804819869736":{"_record":{"data":{"h":{}}},"name":"haxeui ceramic","threadid":"1209142804819869736","count":1917,"id":243},"1327282355706003488":{"_record":{"data":{"h":{}}},"name":"nextrealm snowfight","threadid":"1327282355706003488","count":39,"id":244},"1347275567824896050":{"_record":{"data":{"h":{}}},"name":"the fixed version","threadid":"1347275567824896050","count":63,"id":245},"1347347728266694686":{"_record":{"data":{"h":{}}},"name":"hmm-cpp","threadid":"1347347728266694686","count":14,"id":246},"1083516878468685996":{"_record":{"data":{"h":{}}},"name":"haxeflixel - a free, open-sourced game framework built in haxe!","threadid":"1083516878468685996","count":272,"id":247},"1271093857337085962":{"_record":{"data":{"h":{}}},"name":"ldtk and flxtilemaps","threadid":"1271093857337085962","count":3,"id":248},"1020578706743365632":{"_record":{"data":{"h":{}}},"name":"go2hx","threadid":"1020578706743365632","count":23,"id":249},"1351282686832021505":{"_record":{"data":{"h":{}}},"name":"twinspire web - a html-first, macro based web framework","threadid":"1351282686832021505","count":4,"id":250},"1352337467726102590":{"_record":{"data":{"h":{}}},"name":":d","threadid":"1352337467726102590","count":5,"id":251},"1185591971071406253":{"_record":{"data":{"h":{}}},"name":"haxeget: the easier way to install and manage haxe compiler versions","threadid":"1185591971071406253","count":5,"id":252},"1354569616399270111":{"_record":{"data":{"h":{}}},"name":"epikowa epipure","threadid":"1354569616399270111","count":1,"id":253},"1355275040475709482":{"_record":{"data":{"h":{}}},"name":"cpphelpers","threadid":"1355275040475709482","count":33,"id":254},"1355717152828686537":{"_record":{"data":{"h":{}}},"name":"snake language","threadid":"1355717152828686537","count":7,"id":255},"1355926901926920395":{"_record":{"data":{"h":{}}},"name":"i see that it was last updated 2 years","threadid":"1355926901926920395","count":2,"id":256},"1356580966835163149":{"_record":{"data":{"h":{}}},"name":"add","threadid":"1356580966835163149","count":1,"id":257},"1356582209833930852":{"_record":{"data":{"h":{}}},"name":"add","threadid":"1356582209833930852","count":56,"id":258},"1357799687888965802":{"_record":{"data":{"h":{}}},"name":"either manually or there's this but i've","threadid":"1357799687888965802","count":26,"id":259},"1358153057548112044":{"_record":{"data":{"h":{}}},"name":"coding my dream game in 2025! (and more)","threadid":"1358153057548112044","count":3,"id":260},"1358398963748700274":{"_record":{"data":{"h":{}}},"name":"why does everything i make explode part","threadid":"1358398963748700274","count":18,"id":261},"1358510021872455782":{"_record":{"data":{"h":{}}},"name":"relocation failed","threadid":"1358510021872455782","count":2,"id":262},"1358610571280515237":{"_record":{"data":{"h":{}}},"name":"ld57 compo submitted https://ldjam.com/","threadid":"1358610571280515237","count":11,"id":263},"1357700514816458924":{"_record":{"data":{"h":{}}},"name":"https://haxeui.org/builder/?789bab90","threadid":"1357700514816458924","count":2,"id":264},"1358912105104932935":{"_record":{"data":{"h":{}}},"name":"at the moment i'm using it for proximity","threadid":"1358912105104932935","count":9,"id":265},"1358962003661684897":{"_record":{"data":{"h":{}}},"name":"untitled 4-key rhythm game","threadid":"1358962003661684897","count":77,"id":266},"1359095318708228227":{"_record":{"data":{"h":{}}},"name":"<https://haxeui.org/builder/?789bab90>","threadid":"1359095318708228227","count":5,"id":267},"1360530058959126549":{"_record":{"data":{"h":{}}},"name":".","threadid":"1360530058959126549","count":26,"id":268},"1361169616587460669":{"_record":{"data":{"h":{}}},"name":"full stack developer and ux/ui designer is ready to work with you","threadid":"1361169616587460669","count":3,"id":269},"1279194571116646471":{"_record":{"data":{"h":{}}},"name":"haxeflixel-utils","threadid":"1279194571116646471","count":3,"id":270},"1240429122887483463":{"_record":{"data":{"h":{}}},"name":"dimo engine!","threadid":"1240429122887483463","count":1,"id":271},"1285240246459695216":{"_record":{"data":{"h":{}}},"name":"good","threadid":"1285240246459695216","count":51,"id":272},"1362619355812335616":{"_record":{"data":{"h":{}}},"name":"sinco and portilizen (help wanted)","threadid":"1362619355812335616","count":147,"id":273},"1363568455470809131":{"_record":{"data":{"h":{}}},"name":"ever wanted to get your art harshly","threadid":"1363568455470809131","count":18,"id":274},"1363596088619303003":{"_record":{"data":{"h":{}}},"name":"references","threadid":"1363596088619303003","count":4,"id":275},"1363599728616538153":{"_record":{"data":{"h":{}}},"name":"nothing too fancy, but wanna join the","threadid":"1363599728616538153","count":7,"id":276},"1363855011263549640":{"_record":{"data":{"h":{}}},"name":"dogpaint","threadid":"1363855011263549640","count":27,"id":277},"1364015487733727233":{"_record":{"data":{"h":{}}},"name":"super pixel guy 3d","threadid":"1364015487733727233","count":910,"id":278},"1364672665758994473":{"_record":{"data":{"h":{}}},"name":"flixelmodding hotfix might be a little","threadid":"1364672665758994473","count":55,"id":279},"1364744236032852028":{"_record":{"data":{"h":{}}},"name":"pickle frickle","threadid":"1364744236032852028","count":15,"id":280},"1365760450930675893":{"_record":{"data":{"h":{}}},"name":"behavior trees","threadid":"1365760450930675893","count":68,"id":281},"1366119876082798686":{"_record":{"data":{"h":{}}},"name":"luvi","threadid":"1366119876082798686","count":8,"id":282},"1367138149259673712":{"_record":{"data":{"h":{}}},"name":"flixel-modding - a robust modding system for haxeflixel.","threadid":"1367138149259673712","count":1177,"id":283},"1367163057092034600":{"_record":{"data":{"h":{}}},"name":"we are looking for programmers with therequirements shown in this post:","threadid":"1367163057092034600","count":2,"id":284},"1182083476506296371":{"_record":{"data":{"h":{}}},"name":"flxwiimenu","threadid":"1182083476506296371","count":20,"id":285},"1368695819422928897":{"_record":{"data":{"h":{}}},"name":"subtract","threadid":"1368695819422928897","count":64,"id":286},"1369056340579713155":{"_record":{"data":{"h":{}}},"name":"hl-luajit","threadid":"1369056340579713155","count":3,"id":287},"1369121359585869845":{"_record":{"data":{"h":{}}},"name":"prismcli","threadid":"1369121359585869845","count":41,"id":288},"1369449420495650977":{"_record":{"data":{"h":{}}},"name":"hxtomlc17","threadid":"1369449420495650977","count":14,"id":289},"1369479696357527623":{"_record":{"data":{"h":{}}},"name":"lazylambda – a functional iterators library","threadid":"1369479696357527623","count":5,"id":290},"1370479574021967983":{"_record":{"data":{"h":{}}},"name":"can someone help me understand how to","threadid":"1370479574021967983","count":68,"id":291},"1370791933752115321":{"_record":{"data":{"h":{}}},"name":"network game with haxeflixel","threadid":"1370791933752115321","count":21,"id":292},"1370873727348113408":{"_record":{"data":{"h":{}}},"name":"wizards against the horde","threadid":"1370873727348113408","count":7,"id":293},"1370925492189925446":{"_record":{"data":{"h":{}}},"name":"solar engine","threadid":"1370925492189925446","count":17,"id":294},"1372771213851754646":{"_record":{"data":{"h":{}}},"name":"undertale boundfate","threadid":"1372771213851754646","count":3845,"id":295},"1373191308805410857":{"_record":{"data":{"h":{}}},"name":"haxe × godot","threadid":"1373191308805410857","count":54,"id":296},"1373789048283467827":{"_record":{"data":{"h":{}}},"name":"cpp2hl","threadid":"1373789048283467827","count":41,"id":297},"1282493664068767825":{"_record":{"data":{"h":{}}},"name":"ludum dare 56 collab","threadid":"1282493664068767825","count":11,"id":298},"1375267793053814856":{"_record":{"data":{"h":{}}},"name":"lumina/beacon","threadid":"1375267793053814856","count":288,"id":299},"1375481859898867873":{"_record":{"data":{"h":{}}},"name":"omnitrix showcase/test","threadid":"1375481859898867873","count":4,"id":300},"1375882050799796325":{"_record":{"data":{"h":{}}},"name":"sonic in haxeflixel","threadid":"1375882050799796325","count":5,"id":301},"1375884930516521012":{"_record":{"data":{"h":{}}},"name":"sonic framework","threadid":"1375884930516521012","count":23,"id":302},"1376587572536676724":{"_record":{"data":{"h":{}}},"name":"hxenkits - haxe/hxcpp @:native bindings for enkitd","threadid":"1376587572536676724","count":25,"id":303},"1376701121338544208":{"_record":{"data":{"h":{}}},"name":"@aurel300 is there an equivalent to","threadid":"1376701121338544208","count":4,"id":304},"1376895146200797264":{"_record":{"data":{"h":{}}},"name":"thread","threadid":"1376895146200797264","count":2,"id":305},"1377707839103176775":{"_record":{"data":{"h":{}}},"name":"harrow","threadid":"1377707839103176775","count":19,"id":306},"1377886594475884594":{"_record":{"data":{"h":{}}},"name":"possible  mini framework ontop of hxsdl?","threadid":"1377886594475884594","count":125,"id":307},"1377948589694910555":{"_record":{"data":{"h":{}}},"name":"a small demo of my engine","threadid":"1377948589694910555","count":3,"id":308},"1378148952679125054":{"_record":{"data":{"h":{"id":309,"name":"webossan stuff","threadid":"1378148952679125054","count":4586}}},"name":"webossan stuff","threadid":"1378148952679125054","count":4586,"id":309},"1378396556004294676":{"_record":{"data":{"h":{}}},"name":"ini.hx","threadid":"1378396556004294676","count":5,"id":310},"1378772000058904717":{"_record":{"data":{"h":{}}},"name":"weirdbot","threadid":"1378772000058904717","count":13,"id":311},"1378785622415642634":{"_record":{"data":{"h":{}}},"name":"compile problem","threadid":"1378785622415642634","count":19,"id":312},"1378876256095047750":{"_record":{"data":{"h":{}}},"name":"equality.hx","threadid":"1378876256095047750","count":8,"id":313},"1378908093198373015":{"_record":{"data":{"h":{}}},"name":"akaira's love match ~ game from holojam","threadid":"1378908093198373015","count":2,"id":314},"1378930730649780245":{"_record":{"data":{"h":{}}},"name":"lfsnake: flxsnake for the wii u","threadid":"1378930730649780245","count":2,"id":315},"1186414058358980618":{"_record":{"data":{"h":{}}},"name":"megaman zero but in flixel","threadid":"1186414058358980618","count":1,"id":316},"1379267213734838292":{"_record":{"data":{"h":{}}},"name":"seeking unity c# developer for defi-integrated game","threadid":"1379267213734838292","count":7,"id":317},"1379909346997043240":{"_record":{"data":{"h":{}}},"name":"forest text adventure","threadid":"1379909346997043240","count":24,"id":318},"1380698032319762482":{"_record":{"data":{"h":{}}},"name":"and also, i said i had a deadline, so","threadid":"1380698032319762482","count":19,"id":319},"1381271179494424626":{"_record":{"data":{"h":{}}},"name":"working on a small toy scripting","threadid":"1381271179494424626","count":19,"id":320},"1381705165572276346":{"_record":{"data":{"h":{}}},"name":"satisfactory","threadid":"1381705165572276346","count":45,"id":321},"1381836415004049528":{"_record":{"data":{"h":{}}},"name":"sdm - soda's dependency manager inspired by hmm and hxpkg","threadid":"1381836415004049528","count":5,"id":322},"1382087028958691502":{"_record":{"data":{"h":{}}},"name":"heaps-bms fork","threadid":"1382087028958691502","count":10,"id":323},"1382353481960259695":{"_record":{"data":{"h":{}}},"name":"@pxshadow - the copper shortage begins:","threadid":"1382353481960259695","count":25,"id":324},"1382560253740056658":{"_record":{"data":{"h":{}}},"name":"fizik by sunny","threadid":"1382560253740056658","count":3,"id":325},"1383109086463135815":{"_record":{"data":{"h":{}}},"name":"flxdeltarune","threadid":"1383109086463135815","count":829,"id":326},"1383138111516840017":{"_record":{"data":{"h":{}}},"name":"introducing gtween for haxe","threadid":"1383138111516840017","count":4,"id":327},"1383417949569683536":{"_record":{"data":{"h":{}}},"name":"undertale brown","threadid":"1383417949569683536","count":10,"id":328},"1383550678106112181":{"_record":{"data":{"h":{}}},"name":"my 2d/3d painting program demo","threadid":"1383550678106112181","count":8,"id":329},"1384209725994045571":{"_record":{"data":{"h":{}}},"name":"github - mattonesss/flxdebug: a haxeflix...","threadid":"1384209725994045571","count":3,"id":330},"1385414324943585331":{"_record":{"data":{"h":{}}},"name":"sizing a custom flixel component","threadid":"1385414324943585331","count":45,"id":331},"1286692718520701051":{"_record":{"data":{"h":{}}},"name":"manaframework [wip / progress thread]","threadid":"1286692718520701051","count":1952,"id":332},"1386427891071451276":{"_record":{"data":{"h":{}}},"name":"flixel-animate","threadid":"1386427891071451276","count":82,"id":333},"1386443157369131079":{"_record":{"data":{"h":{}}},"name":"unity 6 using latest universal render pipeline + render graph","threadid":"1386443157369131079","count":1,"id":334},"1386550125295571026":{"_record":{"data":{"h":{}}},"name":"forget that old video srd, new one with","threadid":"1386550125295571026","count":3,"id":335},"1387079407000223754":{"_record":{"data":{"h":{}}},"name":"language support","threadid":"1387079407000223754","count":76,"id":336},"1387119783773732864":{"_record":{"data":{"h":{}}},"name":"undertale green","threadid":"1387119783773732864","count":60,"id":337},"1387482733860753548":{"_record":{"data":{"h":{}}},"name":"in glsl, do ternary operators have the","threadid":"1387482733860753548","count":30,"id":338},"1389186460774568007":{"_record":{"data":{"h":{}}},"name":"hscript","threadid":"1389186460774568007","count":16,"id":339},"1389576490508746862":{"_record":{"data":{"h":{}}},"name":"hxfilemanager","threadid":"1389576490508746862","count":69,"id":340},"1390363669056983071":{"_record":{"data":{"h":{}}},"name":"github - pursnake/flxrhythmconductor: fr...","threadid":"1390363669056983071","count":8,"id":341},"1391441219069935647":{"_record":{"data":{"h":{}}},"name":"twinspire core - the modern, extensible, low-level framework for kha","threadid":"1391441219069935647","count":9,"id":342},"1391472905933684849":{"_record":{"data":{"h":{}}},"name":"baldis basics but in flixel with away3d","threadid":"1391472905933684849","count":23,"id":343},"1392562992142614600":{"_record":{"data":{"h":{}}},"name":"dreamland","threadid":"1392562992142614600","count":72,"id":344},"1393013794090782811":{"_record":{"data":{"h":{}}},"name":"congrats!","threadid":"1393013794090782811","count":2,"id":345},"1393969087788351629":{"_record":{"data":{"h":{}}},"name":"[magic array tools v2.0](https://github.","threadid":"1393969087788351629","count":98,"id":346},"1394024743983906947":{"_record":{"data":{"h":{}}},"name":"[help wanted] a small space game im working on","threadid":"1394024743983906947","count":1,"id":347},"1394408424057471117":{"_record":{"data":{"h":{}}},"name":"phase through floor","threadid":"1394408424057471117","count":79,"id":348},"1394665560398233742":{"_record":{"data":{"h":{}}},"name":"flxdebug","threadid":"1394665560398233742","count":5,"id":349},"1395963801546784819":{"_record":{"data":{"h":{}}},"name":"why flxspritecontainer is like that","threadid":"1395963801546784819","count":1,"id":350},"1396925849927942364":{"_record":{"data":{"h":{}}},"name":"juil - just ui layouts","threadid":"1396925849927942364","count":23,"id":351},"1399087304085344369":{"_record":{"data":{"h":{}}},"name":"endbi","threadid":"1399087304085344369","count":6,"id":352},"1399843559397392424":{"_record":{"data":{"h":{}}},"name":"jlang","threadid":"1399843559397392424","count":173,"id":353},"1399453186158362675":{"_record":{"data":{"h":{}}},"name":"wordle","threadid":"1399453186158362675","count":11,"id":354},"1400520036010954872":{"_record":{"data":{"h":{}}},"name":"ropasci [playtesting period]","threadid":"1400520036010954872","count":10,"id":355},"1400653897705717890":{"_record":{"data":{"h":{}}},"name":"is this code good?","threadid":"1400653897705717890","count":14,"id":356},"1400901424195305523":{"_record":{"data":{"h":{}}},"name":"8pix","threadid":"1400901424195305523","count":1,"id":357},"1401749600087441450":{"_record":{"data":{"h":{}}},"name":"this is where i’m getting stuck btw","threadid":"1401749600087441450","count":11,"id":358},"1401917084044365834":{"_record":{"data":{"h":{}}},"name":"fluesend - multiplayer library","threadid":"1401917084044365834","count":42,"id":359},"1402040607211524166":{"_record":{"data":{"h":{}}},"name":"diavy","threadid":"1402040607211524166","count":49,"id":360},"1403018363227082843":{"_record":{"data":{"h":{}}},"name":"tinyexterns","threadid":"1403018363227082843","count":294,"id":361},"1403205134053539840":{"_record":{"data":{"h":{}}},"name":"miniaudio test","threadid":"1403205134053539840","count":2,"id":362},"1403424729238470726":{"_record":{"data":{"h":{}}},"name":"tick: tactical infiltration and cyber kleptomania","threadid":"1403424729238470726","count":24,"id":363},"1403684039491059743":{"_record":{"data":{"h":{}}},"name":"hypha (haxejam 2025 summer jam)","threadid":"1403684039491059743","count":8,"id":364},"1404069787352563823":{"_record":{"data":{"h":{}}},"name":"sphis","threadid":"1404069787352563823","count":18,"id":365},"1404306970655330385":{"_record":{"data":{"h":{}}},"name":"i concede that @ninjamuffin99 is right","threadid":"1404306970655330385","count":3,"id":366},"1404767688429015131":{"_record":{"data":{"h":{}}},"name":"4am","threadid":"1404767688429015131","count":5,"id":367},"1405209722075873380":{"_record":{"data":{"h":{}}},"name":"created a \"wrapper\" around movieclip to","threadid":"1405209722075873380","count":6,"id":368},"1405141462450049025":{"_record":{"data":{"h":{}}},"name":"i'm using armory 3d for my own project","threadid":"1405141462450049025","count":15,"id":369},"1405419534529204244":{"_record":{"data":{"h":{}}},"name":"leafy engine: the game engine for the wii u made with haxe","threadid":"1405419534529204244","count":39,"id":370},"1405689815860510791":{"_record":{"data":{"h":{}}},"name":"heaps debug server (proof of concept)","threadid":"1405689815860510791","count":1,"id":371},"1406641815053926602":{"_record":{"data":{"h":{}}},"name":"failed to load function ma_thing#amplify_decoder_hl","threadid":"1406641815053926602","count":131,"id":372},"1406807533879820370":{"_record":{"data":{"h":{}}},"name":"hashlink c++ equivalent of array<string> help","threadid":"1406807533879820370","count":10,"id":373},"1407043908675960984":{"_record":{"data":{"h":{}}},"name":"syobon action advance","threadid":"1407043908675960984","count":105,"id":374},"1407072912955015228":{"_record":{"data":{"h":{}}},"name":"hashlink-only error: abstract haxe.ds.map has no @:to function that accepts haxe.imap<..., ...>","threadid":"1407072912955015228","count":15,"id":375},"1407774831927103549":{"_record":{"data":{"h":{}}},"name":"fruit world","threadid":"1407774831927103549","count":52,"id":376},"1408547360908382268":{"_record":{"data":{"h":{}}},"name":"rooted in love","threadid":"1408547360908382268","count":35,"id":377},"1410401465499123732":{"_record":{"data":{"h":{"id":378,"name":"haxe3ds","threadid":"1410401465499123732","count":318}}},"name":"haxe3ds","threadid":"1410401465499123732","count":318,"id":378},"1411101007013744742":{"_record":{"data":{"h":{}}},"name":"ultimate sonic haxeflixel","threadid":"1411101007013744742","count":20,"id":379},"1411536223549526139":{"_record":{"data":{"h":{}}},"name":"msg's workflow is kinda nice now","threadid":"1411536223549526139","count":224,"id":380},"1412126552522752100":{"_record":{"data":{"h":{}}},"name":"sphis: avly","threadid":"1412126552522752100","count":17,"id":381},"1412871907598008482":{"_record":{"data":{"h":{}}},"name":"chant: a haxe audio library","threadid":"1412871907598008482","count":107,"id":382},"1412933145203839076":{"_record":{"data":{"h":{}}},"name":"convert array to std::vector","threadid":"1412933145203839076","count":12,"id":383},"1413261349177397361":{"_record":{"data":{"h":{}}},"name":"using haxe, flixel and the hxserial_api","threadid":"1413261349177397361","count":3,"id":384},"1413624979765071953":{"_record":{"data":{"h":{}}},"name":"personalities: haxen","threadid":"1413624979765071953","count":50,"id":385},"1414024432321826968":{"_record":{"data":{"h":{}}},"name":"citroengine","threadid":"1414024432321826968","count":5,"id":386},"1414083727222636674":{"_record":{"data":{"h":{}}},"name":"problem on my class generator macro","threadid":"1414083727222636674","count":4,"id":387},"1414578370909442199":{"_record":{"data":{"h":{}}},"name":"i'd probably play with rust too if haxe","threadid":"1414578370909442199","count":14,"id":388},"1119775060266332251":{"_record":{"data":{"h":{}}},"name":"3dshaxe","threadid":"1119775060266332251","count":8,"id":389},"1415732031878463489":{"_record":{"data":{"h":{}}},"name":"autostash - (apprenticeship project)","threadid":"1415732031878463489","count":26,"id":390},"1416231701767782491":{"_record":{"data":{"h":{}}},"name":"sphis: ontime","threadid":"1416231701767782491","count":3,"id":391},"1417565040503951523":{"_record":{"data":{"h":{}}},"name":"haxenxcompiler","threadid":"1417565040503951523","count":2367,"id":392},"1418384696072736888":{"_record":{"data":{"h":{}}},"name":"some game i'm making","threadid":"1418384696072736888","count":28,"id":393},"1419575651827978352":{"_record":{"data":{"h":{}}},"name":"antriel's macros spring cleaning aka make things work","threadid":"1419575651827978352","count":296,"id":394},"1420084433066918099":{"_record":{"data":{"h":{}}},"name":"flixel-swift","threadid":"1420084433066918099","count":7,"id":395},"1420086055104811120":{"_record":{"data":{"h":{}}},"name":"hx-anim","threadid":"1420086055104811120","count":1,"id":396},"1420209509430726737":{"_record":{"data":{"h":{}}},"name":"🌙🛏 toffee's cozy room","threadid":"1420209509430726737","count":21,"id":397},"1420395696913256560":{"_record":{"data":{"h":{}}},"name":"flying.haxe's sleepy project room","threadid":"1420395696913256560","count":287,"id":398},"1420583374883393611":{"_record":{"data":{"h":{}}},"name":"paliverge","threadid":"1420583374883393611","count":16,"id":399},"1420824057301172357":{"_record":{"data":{"h":{}}},"name":"flxundertale","threadid":"1420824057301172357","count":22,"id":400},"1421545594325045429":{"_record":{"data":{"h":{}}},"name":"viwu shot","threadid":"1421545594325045429","count":16,"id":401},"1422666978694533181":{"_record":{"data":{"h":{}}},"name":"char's song visualizer","threadid":"1422666978694533181","count":11,"id":402},"1423069287488163953":{"_record":{"data":{"h":{}}},"name":"riryk maker","threadid":"1423069287488163953","count":11,"id":403},"1423129807511752868":{"_record":{"data":{"h":{}}},"name":".","threadid":"1423129807511752868","count":9,"id":404},"1424469241318342757":{"_record":{"data":{"h":{}}},"name":"the sphis site","threadid":"1424469241318342757","count":22,"id":405},"1425576453419831437":{"_record":{"data":{"h":{}}},"name":"zz3d","threadid":"1425576453419831437","count":6,"id":406},"1427053699339124849":{"_record":{"data":{"h":{}}},"name":"working on a custom physics \"engine\" in","threadid":"1427053699339124849","count":4,"id":407},"1428751335276155032":{"_record":{"data":{"h":{}}},"name":"tree-sitter-haxe/hxml","threadid":"1428751335276155032","count":37,"id":408},"1429563383212150784":{"_record":{"data":{"h":{}}},"name":"hscript-rewrite/bytecode for hscript","threadid":"1429563383212150784","count":404,"id":409},"1430409580952817665":{"_record":{"data":{"h":{"id":410,"name":"nxscript - bytecode stack based language","threadid":"1430409580952817665","count":1754}}},"name":"nxscript - bytecode stack based language","threadid":"1430409580952817665","count":1754,"id":410},"1430562333742071980":{"_record":{"data":{"h":{}}},"name":"working on a pvz port and almost ported","threadid":"1430562333742071980","count":9,"id":411},"1430637607288701090":{"_record":{"data":{"h":{}}},"name":"unnamed office sim","threadid":"1430637607288701090","count":49,"id":412},"1430800132823060510":{"_record":{"data":{"h":{}}},"name":"alchimix","threadid":"1430800132823060510","count":36,"id":413},"1431213067240341607":{"_record":{"data":{"h":{}}},"name":"my attempt to make a pacman and aur","threadid":"1431213067240341607","count":7,"id":414},"1435642167698915348":{"_record":{"data":{"h":{}}},"name":"function assigned to variable","threadid":"1435642167698915348","count":31,"id":415},"1436132035239346207":{"_record":{"data":{"h":{}}},"name":"hmmm (hmm maker)","threadid":"1436132035239346207","count":7,"id":416},"1436176800479973537":{"_record":{"data":{"h":{}}},"name":"ui thingies lol","threadid":"1436176800479973537","count":1,"id":417},"1436399067994263663":{"_record":{"data":{"h":{}}},"name":"yo, is cpp.int64map faster than map<int64, t>?","threadid":"1436399067994263663","count":5,"id":418},"1436839415694622932":{"_record":{"data":{"h":{}}},"name":"frixuu's wip toy web server (apricot)","threadid":"1436839415694622932","count":2,"id":419},"1437137907839143946":{"_record":{"data":{"h":{}}},"name":"coding a physics engine from scratch!","threadid":"1437137907839143946","count":43,"id":420},"1437148507436879993":{"_record":{"data":{"h":{}}},"name":"glint analytics example dashboards...","threadid":"1437148507436879993","count":6,"id":421},"1437607633891622922":{"_record":{"data":{"h":{}}},"name":"@a js nerd (get it? cause haxe?)","threadid":"1437607633891622922","count":2,"id":422},"1438464951550214226":{"_record":{"data":{"h":{}}},"name":"my ongoing armory 3d project quest of raziya","threadid":"1438464951550214226","count":4,"id":423},"962735230475698246":{"_record":{"data":{"h":{}}},"name":"squeak and smalltalk","threadid":"962735230475698246","count":1,"id":424},"1439272685015269386":{"_record":{"data":{"h":{}}},"name":"i don't think much of the openal api was","threadid":"1439272685015269386","count":66,"id":425},"1439372597627191326":{"_record":{"data":{"h":{}}},"name":"firebase crashlytics extension for lime","threadid":"1439372597627191326","count":1,"id":426},"1439465849042767932":{"_record":{"data":{"h":{}}},"name":"rfid music server with admin ui","threadid":"1439465849042767932","count":2,"id":427},"1442927003534753914":{"_record":{"data":{"h":{}}},"name":"winter is coming @logo","threadid":"1442927003534753914","count":3,"id":428},"1443168498116329566":{"_record":{"data":{"h":{}}},"name":"webp in haxe...","threadid":"1443168498116329566","count":5,"id":429},"1443676390695370752":{"_record":{"data":{"h":{}}},"name":"suvindo","threadid":"1443676390695370752","count":23,"id":430},"1444169854939697242":{"_record":{"data":{"h":{}}},"name":"\"a poor imitation\" (a song) and haxe on nintendo ds...?","threadid":"1444169854939697242","count":9,"id":431},"1045089472204779531":{"_record":{"data":{"h":{}}},"name":"g-switch 4: creator","threadid":"1045089472204779531","count":1,"id":432},"1446287547109085285":{"_record":{"data":{"h":{}}},"name":"sick ui","threadid":"1446287547109085285","count":6,"id":433},"1446321392671785140":{"_record":{"data":{"h":{}}},"name":"ale ui","threadid":"1446321392671785140","count":9,"id":434},"1447317776053309591":{"_record":{"data":{"h":{}}},"name":"hxluau - roblox lua engine","threadid":"1447317776053309591","count":11,"id":435},"1447859935085068370":{"_record":{"data":{"h":{}}},"name":"scatterplan","threadid":"1447859935085068370","count":7,"id":436},"1448218026137882704":{"_record":{"data":{"h":{}}},"name":"i register the print function","threadid":"1448218026137882704","count":47,"id":437},"1448333862584189070":{"_record":{"data":{"h":{}}},"name":"how do enums work on haxe?","threadid":"1448333862584189070","count":2,"id":438},"1448607525409919046":{"_record":{"data":{"h":{}}},"name":"roblox-hx / reflaxe.lua","threadid":"1448607525409919046","count":21,"id":439},"1449396298913415311":{"_record":{"data":{"h":{}}},"name":"fiouth","threadid":"1449396298913415311","count":47,"id":440},"1449605908857356430":{"_record":{"data":{"h":{}}},"name":"float returning functions just return 0.","threadid":"1449605908857356430","count":5,"id":441},"1450566380595318938":{"_record":{"data":{"h":{}}},"name":"lune: blazingly slow lua interpreter :snail: :snail: :snail:","threadid":"1450566380595318938","count":229,"id":442},"1452494347747459093":{"_record":{"data":{"h":{}}},"name":"simple web live multiplayer server","threadid":"1452494347747459093","count":1,"id":443},"1453271267418308690":{"_record":{"data":{"h":{}}},"name":"📦 swordcube's toybox 🧸","threadid":"1453271267418308690","count":89,"id":444},"1453669277532946553":{"_record":{"data":{"h":{}}},"name":"tepro","threadid":"1453669277532946553","count":88,"id":445},"1454201162374058206":{"_record":{"data":{"h":{}}},"name":"the thing is, i'm having trouble","threadid":"1454201162374058206","count":1,"id":446},"1454807109269979268":{"_record":{"data":{"h":{}}},"name":"furryscript","threadid":"1454807109269979268","count":1196,"id":447},"1455268791138127986":{"_record":{"data":{"h":{}}},"name":"please any help in vsc auto complete","threadid":"1455268791138127986","count":92,"id":448},"1455430111321915426":{"_record":{"data":{"h":{}}},"name":"sinco and portilizen 3+","threadid":"1455430111321915426","count":17,"id":449},"1455606730460233828":{"_record":{"data":{"h":{}}},"name":"i just have one question","threadid":"1455606730460233828","count":4,"id":450},"1457136837163221143":{"_record":{"data":{"h":{}}},"name":"shadertoy","threadid":"1457136837163221143","count":11,"id":451},"1457178550645031074":{"_record":{"data":{"h":{}}},"name":"useful multi-platfrom logging library","threadid":"1457178550645031074","count":1,"id":452},"1458176568340774995":{"_record":{"data":{"h":{}}},"name":"hazel - language server for haxe","threadid":"1458176568340774995","count":33,"id":453},"1458384997009457326":{"_record":{"data":{"h":{}}},"name":"haxescript","threadid":"1458384997009457326","count":4,"id":454},"1458833657233149952":{"_record":{"data":{"h":{}}},"name":"next problem. i have a haxe object","threadid":"1458833657233149952","count":2,"id":455},"1458866312850968618":{"_record":{"data":{"h":{}}},"name":"neovim haxe lsp plugin","threadid":"1458866312850968618","count":1,"id":456},"1459470378287235269":{"_record":{"data":{"h":{}}},"name":"openhaxegd","threadid":"1459470378287235269","count":101,"id":457},"1459742407003340845":{"_record":{"data":{"h":{}}},"name":"café ☕","threadid":"1459742407003340845","count":38,"id":458},"1459759376540635361":{"_record":{"data":{"h":{}}},"name":"niz messy stuff","threadid":"1459759376540635361","count":1592,"id":459},"1460670936314417212":{"_record":{"data":{"h":{}}},"name":"osakared - twitch","threadid":"1460670936314417212","count":13,"id":460},"1223317744519352422":{"_record":{"data":{"h":{}}},"name":"diced up!","threadid":"1223317744519352422","count":5,"id":461},"1463533082157121648":{"_record":{"data":{"h":{}}},"name":"lumi - a game engine with a web and love2d backend","threadid":"1463533082157121648","count":5,"id":462},"1463578929662001173":{"_record":{"data":{"h":{}}},"name":"are there examples for generating sounds","threadid":"1463578929662001173","count":58,"id":463},"1467176873908899851":{"_record":{"data":{"h":{}}},"name":"onfocus doesn't work","threadid":"1467176873908899851","count":21,"id":464},"1467773368932761600":{"_record":{"data":{"h":{}}},"name":"hxpvz","threadid":"1467773368932761600","count":8,"id":465},"1467854844416233494":{"_record":{"data":{"h":{}}},"name":"all the way up","threadid":"1467854844416233494","count":32,"id":466},"1468270439280279815":{"_record":{"data":{"h":{}}},"name":"habit puzzles","threadid":"1468270439280279815","count":9,"id":467},"1469098369619333231":{"_record":{"data":{"h":{}}},"name":"flxisaac: repentance","threadid":"1469098369619333231","count":21,"id":468},"1469332770647052571":{"_record":{"data":{"h":{}}},"name":"colyseus - multiplayer framework","threadid":"1469332770647052571","count":2,"id":469},"1470068144763699220":{"_record":{"data":{"h":{}}},"name":"hello algo for haxe","threadid":"1470068144763699220","count":2,"id":470},"1470189755655393352":{"_record":{"data":{"h":{}}},"name":"tuna - a opengl / webgl library in haxe (and other things made in it)","threadid":"1470189755655393352","count":292,"id":471},"1470432616216789022":{"_record":{"data":{"h":{}}},"name":"niz is not here dont enter","threadid":"1470432616216789022","count":23,"id":472},"1470179223351202026":{"_record":{"data":{"h":{}}},"name":"add opus audio format support by dtwotwo...","threadid":"1470179223351202026","count":1,"id":473},"1052688097592225904":{"_record":{"data":{"h":{}}},"name":"reflaxe - reflection compiler for haxe","threadid":"1052688097592225904","count":7,"id":474},"1471947842418639132":{"_record":{"data":{"h":{}}},"name":"macohi animated interactive","threadid":"1471947842418639132","count":3,"id":475},"1472011185241985207":{"_record":{"data":{"h":{}}},"name":"amp - autistic media player","threadid":"1472011185241985207","count":7,"id":476},"1472372604433076446":{"_record":{"data":{"h":{}}},"name":"haxe-fmod 1.0.0 beta release! (integration for fmod studio / fmod)","threadid":"1472372604433076446","count":12,"id":477},"1472967373073027274":{"_record":{"data":{"h":{}}},"name":"dirifin","threadid":"1472967373073027274","count":55,"id":478},"1473371213618479135":{"_record":{"data":{"h":{}}},"name":"slushi's fox room","threadid":"1473371213618479135","count":67,"id":479},"1474431493085331577":{"_record":{"data":{"h":{}}},"name":"🐺 antriel's stuff","threadid":"1474431493085331577","count":34,"id":480},"1475242607910195270":{"_record":{"data":{"h":{}}},"name":"fiberus - a new haxe target with a native, fiber-based runtime for multiprocessing.","threadid":"1475242607910195270","count":163,"id":481},"1476651333816684615":{"_record":{"data":{"h":{}}},"name":"whats a good word for \"something that","threadid":"1476651333816684615","count":1,"id":482},"1477007057310711913":{"_record":{"data":{"h":{}}},"name":"untitled oneshot fan project","threadid":"1477007057310711913","count":58,"id":483},"1477751323578597548":{"_record":{"data":{"h":{}}},"name":"now to clean this code up and move to","threadid":"1477751323578597548","count":5,"id":484},"1479172385826406557":{"_record":{"data":{"h":{}}},"name":"where is a hashlink linux binary","threadid":"1479172385826406557","count":69,"id":485},"1479809474771292261":{"_record":{"data":{"h":{}}},"name":"haxe-ide","threadid":"1479809474771292261","count":16,"id":486},"1479928943585792065":{"_record":{"data":{"h":{}}},"name":"apparently, hashlink in wsl produces","threadid":"1479928943585792065","count":5,"id":487},"1480223340068081776":{"_record":{"data":{"h":{}}},"name":"hython - simple buggy python interpreted","threadid":"1480223340068081776","count":4,"id":488},"1480250724213592187":{"_record":{"data":{"h":{}}},"name":"hi everyone! i'm working on my first","threadid":"1480250724213592187","count":8,"id":489},"1480262021462360198":{"_record":{"data":{"h":{}}},"name":"got search working in my documentation","threadid":"1480262021462360198","count":15,"id":490}}}